{
  "_class": "shapePath",
  "booleanOperation": -1,
  "do_objectID": "4D0D3544-515E-41CC-ABD1-6593EAAC2E39",
  "edited": true,
  "exportOptions": {
    "_class": "exportOptions",
    "exportFormats": [
    ],
    "includedLayerIds": [
    ],
    "layerOptions": 0,
    "shouldTrim": false
  },
  "frame": {
    "_class": "rect",
    "constrainProportions": false,
    "height": 6.544,
    "width": 6.562000000000012,
    "x": 0,
    "y": 0
  },
  "isClosed": false,
  "isFlippedHorizontal": false,
  "isFlippedVertical": false,
  "isLocked": false,
  "isVisible": true,
  "layerListExpandedType": 0,
  "name": "Path",
  "nameIsFixed": false,
  "pointRadiusBehaviour": 1,
  "points": [
    {
      "_class": "curvePoint",
      "cornerRadius": 0,
      "curveFrom": "{0.10911307528192729, 0}",
      "curveMode": 1,
      "curveTo": "{0.10911307528192729, 0}",
      "hasCurveFrom": false,
      "hasCurveTo": false,
      "point": "{0.10911307528192729, 0}"
    },
    {
      "_class": "curvePoint",
      "cornerRadius": 0,
      "curveFrom": "{0, 1}",
      "curveMode": 1,
      "curveTo": "{0, 1}",
      "hasCurveFrom": false,
      "hasCurveTo": false,
      "point": "{0, 1}"
    },
    {
      "_class": "curvePoint",
      "cornerRadius": 0,
      "curveFrom": "{1, 0.84397921760391192}",
      "curveMode": 1,
      "curveTo": "{1, 0.84397921760391192}",
      "hasCurveFrom": false,
      "hasCurveTo": false,
      "point": "{1, 0.84397921760391192}"
    }
  ],
  "resizingConstraint": 63,
  "resizingType": 0,
  "rotation": 0,
  "shouldBreakMaskChain": false
}