{
  "_class": "group",
  "do_objectID": "91AE45B6-89BD-48F0-B02D-483F25FB55EC",
  "exportOptions": {
    "_class": "exportOptions",
    "exportFormats": [
    ],
    "includedLayerIds": [
    ],
    "layerOptions": 0,
    "shouldTrim": false
  },
  "frame": {
    "_class": "rect",
    "constrainProportions": false,
    "height": 34,
    "width": 34,
    "x": 0,
    "y": 0
  },
  "hasClickThrough": false,
  "isFlippedHorizontal": false,
  "isFlippedVertical": false,
  "isLocked": false,
  "isVisible": true,
  "layerListExpandedType": 0,
  "layers": [
    {
      "class": "shapeGroup",
      "id": "DC00B1CF-F29E-4E54-8FEC-68302366EE3F"
    },
    {
      "class": "shapeGroup",
      "id": "E8C75AFA-235A-454B-811A-C4B5EC434144"
    },
    {
      "class": "shapeGroup",
      "id": "490C45BB-91E5-4051-9D97-8B979112B7D4"
    },
    {
      "class": "shapeGroup",
      "id": "DF6DF47A-CA54-4F3A-82B9-A31162BD9F1F"
    },
    {
      "class": "shapeGroup",
      "id": "35B5BD34-E3EB-49C8-8F55-D077881214DA"
    },
    {
      "class": "shapeGroup",
      "id": "1EB5161C-C562-4BC9-AB01-1640689B9746"
    },
    {
      "class": "shapeGroup",
      "id": "DE7361D4-63BA-464D-B989-BB32CEE89DC0"
    },
    {
      "class": "shapeGroup",
      "id": "EA910651-D59E-434F-89BF-065B5AE2F430"
    },
    {
      "class": "shapeGroup",
      "id": "71A63877-40FB-48DC-BD7B-881B90DFF072"
    },
    {
      "class": "shapeGroup",
      "id": "AD5F3FDC-E411-4407-A88B-644DC1B73E6E"
    },
    {
      "class": "shapeGroup",
      "id": "0AE274D7-9605-49AF-8CA8-87FDBE0886ED"
    },
    {
      "class": "shapeGroup",
      "id": "DF8C3CDE-2CFC-4B77-AC78-4FEE013F00DF"
    },
    {
      "class": "shapeGroup",
      "id": "D80C34A2-276B-4F87-89EC-E2F6858A914F"
    },
    {
      "class": "shapeGroup",
      "id": "AE05C197-740A-4C88-8BE3-2CF414CD6341"
    },
    {
      "class": "shapeGroup",
      "id": "F7AC0D33-2960-4A4E-AAC3-09931F149336"
    }
  ],
  "name": "No IMG",
  "nameIsFixed": true,
  "resizingConstraint": 63,
  "resizingType": 0,
  "rotation": 0,
  "shouldBreakMaskChain": false,
  "style": {
    "_class": "style",
    "endDecorationType": 0,
    "miterLimit": 10,
    "startDecorationType": 0
  },
  "userInfo": {
    "com.animaapp.stc-sketch-plugin": {
      "kModelPropertiesKey": {
      }
    }
  }
}